realtime/__init__.py
realtime/channel.py
realtime/connection.py
realtime/exceptions.py
realtime/message.py
realtime/transformers.py
supabase_realtime-0.0.1.dist-info/LICENSE
supabase_realtime-0.0.1.dist-info/WHEEL
supabase_realtime-0.0.1.dist-info/METADATA
supabase_realtime-0.0.1.dist-info/RECORD
