Metadata-Version: 2.1
Name: supabase-realtime
Version: 0.0.1
Summary: Listen to changes on your supabase postgres database.
Home-page: https://github.com/anand2312/supabase-realtime-client
License: MIT
Author: Anand Krishna
Author-email: anandkrishna2312@gmail.com
Requires-Python: >=3.8,<4.0
Classifier: License :: OSI Approved :: MIT License
Classifier: Programming Language :: Python :: 3
Classifier: Programming Language :: Python :: 3.8
Classifier: Programming Language :: Python :: 3.9
Requires-Dist: python-dateutil (>=2.8.1,<3.0.0)
Requires-Dist: websockets (>=9.1,<10.0)
Project-URL: Documentation, https://anand2312.github.io/supabase-realtime-client
Project-URL: Repository, https://github.com/anand2312/supabase-realtime-client
